setup.cfg
setup.py
NOCExec.egg-info/PKG-INFO
NOCExec.egg-info/SOURCES.txt
NOCExec.egg-info/dependency_links.txt
NOCExec.egg-info/requires.txt
NOCExec.egg-info/top_level.txt
nocexec/__init__.py
nocexec/exception.py