Metadata-Version: 1.1
Name: NOCExec
Version: 0.2a0
Summary: Library for automation of management and configuration of network devices.
Home-page: https://github.com/velp/nocexec
Author: Vadim Ponomarev
Author-email: velizarx@gmail.com
License: MIT
Platform: UNKNOWN
Classifier: Development Status :: 3 - Alpha
Classifier: Intended Audience :: Developers
Classifier: Environment :: Plugins
Classifier: License :: OSI Approved :: MIT License
Classifier: Operating System :: Unix
Classifier: Operating System :: MacOS
Classifier: Programming Language :: Python :: 2
Classifier: Programming Language :: Python :: 3
Classifier: Topic :: System :: Networking
Classifier: Topic :: System :: Systems Administration
Classifier: Topic :: Software Development :: Libraries :: Python Modules
